mdbridge/__init__.py
mdbridge/lin2pbn.py
mdbridge/mdbridge2html.py
mdbridge/mdbridge2latex.py
mdbridge-0.4.4.dist-info/LICENSE
mdbridge-0.4.4.dist-info/METADATA
mdbridge-0.4.4.dist-info/WHEEL
mdbridge-0.4.4.dist-info/entry_points.txt
mdbridge-0.4.4.dist-info/top_level.txt
mdbridge-0.4.4.dist-info/RECORD
