Metadata-Version: 2.1
Name: mdbridge
Version: 0.4.4
Summary: markdown extension for bridge PBN & xinrui & bbo
Home-page: https://gitlab.com/xrgopher/mdbridge
Author: xrgopher
Author-email: xrgopher@outlook.com
License: UNKNOWN
Platform: UNKNOWN
Classifier: Programming Language :: Python :: 3
Classifier: License :: OSI Approved :: MIT License
Classifier: Operating System :: OS Independent
Requires-Python: >=3.6
Requires-Dist: xin2pbn
Requires-Dist: pbn2html
